{
  "id": "3a4f65208e0743eb99c43ce70d593dcc",
  "answers": [
    {
      "elm": "typein_1",
      "type": "simple",
      "markType": "item",
      "markedBy": "engine",
      "value": "Was she surprised"
    },
    {
      "elm": "typein_2",
      "type": "simple",
      "markType": "item",
      "markedBy": "engine",
      "value": "Yes, she was"
    },
    {
      "elm": "typein_3",
      "type": "simple",
      "markType": "item",
      "markedBy": "engine",
      "value": "Was she tired"
    },
    {
      "elm": "typein_4",
      "type": "simple",
      "markType": "item",
      "markedBy": "engine",
      "value": "Yes, she was"
    },
    {
      "elm": "typein_5",
      "type": "simple",
      "markType": "item",
      "markedBy": "engine",
      "value": "Was he angry"
    },
    {
      "elm": "typein_6",
      "type": "simple",
      "markType": "item",
      "markedBy": "engine",
      "value": "No, he wasn't"
    }
  ]
}